{
  "country": "turkey",
  "name": "Turkey",
  "users_by_followers": [
    {
      "rank": 1,
      "username": "metatimeofficial",
      "name": "Metatime",
      "avatar": "https://avatars.githubusercontent.com/u/109962392?v=4",
      "profile_url": "https://github.com/metatimeofficial",
      "followers": 18065,
      "public_repos": 2,
      "public_contributions": 0,
      "total_contributions": 0,
      "bio": "The New Standard.",
      "company": "Metatime Technology Inc.",
      "location": "İstanbul, Turkey",
      "twitter": "metatimecom",
      "blog": "https://metatime.com"
    },
    {
      "rank": 2,
      "username": "f",
      "name": "Fatih Kadir Akın",
      "avatar": "https://avatars.githubusercontent.com/u/196477?v=4",
      "profile_url": "https://github.com/f",
      "followers": 9948,
      "public_repos": 264,
      "public_contributions": 2602,
      "total_contributions": 4324,
      "bio": "Building prompts.chat — JavaScript Developer. Ruby Lover. Author. — @GitHub Star.",
      "company": "@Teknasyon ",
      "location": "Istanbul, Turkey",
      "twitter": "fkadev",
      "blog": "http://fka.dev"
    },
    {
      "rank": 3,
      "username": "helallao",
      "name": "Ali Yaşar",
      "avatar": "https://avatars.githubusercontent.com/u/78656003?v=4",
      "profile_url": "https://github.com/helallao",
      "followers": 8172,
      "public_repos": 1,
      "public_contributions": 1612,
      "total_contributions": 3138,
      "bio": null,
      "company": "@Metakorteks",
      "location": "Adana, Turkey",
      "twitter": null,
      "blog": "https://metakorteks.com/"
    },
    {
      "rank": 4,
      "username": "seckinyasar",
      "name": "Seckin Yasar",
      "avatar": "https://avatars.githubusercontent.com/u/86570205?v=4",
      "profile_url": "https://github.com/seckinyasar",
      "followers": 7205,
      "public_repos": 3,
      "public_contributions": 563,
      "total_contributions": 1051,
      "bio": null,
      "company": "@Metakorteks",
      "location": "Turkey",
      "twitter": null,
      "blog": "https://metakorteks.com/"
    },
    {
      "rank": 5,
      "username": "emirkaanozdemr",
      "name": "Emir Kaan Özdemir",
      "avatar": "https://avatars.githubusercontent.com/u/155099794?v=4",
      "profile_url": "https://github.com/emirkaanozdemr",
      "followers": 6033,
      "public_repos": 124,
      "public_contributions": 310,
      "total_contributions": 470,
      "bio": "Data Scientist | Astronomy and Quantum Computing Enthusiast | Founder and Superposition of @Qranscend | Co-Founder of @Lyra-AI-Team | High School Student",
      "company": null,
      "location": "Istanbul, Turkey",
      "twitter": "emirkaanozdemr",
      "blog": ""
    },
    {
      "rank": 6,
      "username": "tayfunerbilen",
      "name": "Tayfun Erbilen",
      "avatar": "https://avatars.githubusercontent.com/u/2500557?v=4",
      "profile_url": "https://github.com/tayfunerbilen",
      "followers": 4193,
      "public_repos": 161,
      "public_contributions": 3354,
      "total_contributions": 6697,
      "bio": "It's all about dreams",
      "company": null,
      "location": "Eskişehir, Turkey",
      "twitter": null,
      "blog": "tayfun.net"
    },
    {
      "rank": 7,
      "username": "orhun",
      "name": "Orhun Parmaksız",
      "avatar": "https://avatars.githubusercontent.com/u/24392180?v=4",
      "profile_url": "https://github.com/orhun",
      "followers": 4094,
      "public_repos": 497,
      "public_contributions": 4401,
      "total_contributions": 4443,
      "bio": "Terminal Chef at @ratatui |\r\n\r\nMaintainer at @archlinux btw  ",
      "company": "@ratatui | @archlinux",
      "location": "Ankara, Turkey",
      "twitter": null,
      "blog": "orhun.dev"
    },
    {
      "rank": 8,
      "username": "themiralay",
      "name": "Enes Can Işık",
      "avatar": "https://avatars.githubusercontent.com/u/53035239?v=4",
      "profile_url": "https://github.com/themiralay",
      "followers": 3129,
      "public_repos": 47,
      "public_contributions": 105899,
      "total_contributions": 106224,
      "bio": "Back-End Engineer / \r\nCrawler Expert /\r\nWeb3 Dev /\r\nAlgo-Trade Dev /",
      "company": "0x0e0.eth",
      "location": "Turkey",
      "twitter": null,
      "blog": "bulldicator.com"
    },
    {
      "rank": 9,
      "username": "borakasmer",
      "name": "Bora KAŞMER",
      "avatar": "https://avatars.githubusercontent.com/u/9459881?v=4",
      "profile_url": "https://github.com/borakasmer",
      "followers": 2914,
      "public_repos": 154,
      "public_contributions": 22,
      "total_contributions": 22,
      "bio": "Bazıları Hayal Eder Bazıları Yapar",
      "company": "KeepnetLabs Cyber Security",
      "location": "Istanbul / Turkey",
      "twitter": "coderbora",
      "blog": "https://borakasmer.com/"
    },
    {
      "rank": 10,
      "username": "Omar95-A",
      "name": "Ömer Akrum",
      "avatar": "https://avatars.githubusercontent.com/u/81801245?v=4",
      "profile_url": "https://github.com/Omar95-A",
      "followers": 2797,
      "public_repos": 12,
      "public_contributions": 0,
      "total_contributions": 0,
      "bio": "Software Engineer | Front-End Developer",
      "company": "Self-employed",
      "location": "İstanbul, Turkey",
      "twitter": null,
      "blog": ""
    },
    {
      "rank": 11,
      "username": "hikalkan",
      "name": "Halil İbrahim Kalkan",
      "avatar": "https://avatars.githubusercontent.com/u/1210527?v=4",
      "profile_url": "https://github.com/hikalkan",
      "followers": 2770,
      "public_repos": 34,
      "public_contributions": 1165,
      "total_contributions": 1929,
      "bio": "Sofware architect, developer and entrepreneur (@volosoft).",
      "company": "Volosoft",
      "location": "Istanbul, Turkey",
      "twitter": "hibrahimkalkan",
      "blog": "https://halilibrahimkalkan.com"
    },
    {
      "rank": 12,
      "username": "cobanov",
      "name": "Mert Cobanov",
      "avatar": "https://avatars.githubusercontent.com/u/29142615?v=4",
      "profile_url": "https://github.com/cobanov",
      "followers": 2485,
      "public_repos": 63,
      "public_contributions": 567,
      "total_contributions": 974,
      "bio": "Senior AI Engineer & Generative Artist",
      "company": "@RefikAnadolStudio ",
      "location": "Turkey",
      "twitter": "mertcobanov",
      "blog": "cobanov.dev"
    },
    {
      "rank": 13,
      "username": "buraksenyurt",
      "name": "Burak Selim Senyurt",
      "avatar": "https://avatars.githubusercontent.com/u/2705782?v=4",
      "profile_url": "https://github.com/buraksenyurt",
      "followers": 2372,
      "public_repos": 103,
      "public_contributions": 1476,
      "total_contributions": 1476,
      "bio": "Matematik Mühendisi, MBAci, eski MVP, blogger, @nedirtv editörü. Turuncu sakallı bir yazılım geliştirici.",
      "company": "@DogusTeknoloji",
      "location": "Turkey",
      "twitter": null,
      "blog": "https://www.buraksenyurt.com"
    },
    {
      "rank": 14,
      "username": "meseven",
      "name": "Mehmet Seven",
      "avatar": "https://avatars.githubusercontent.com/u/1716620?v=4",
      "profile_url": "https://github.com/meseven",
      "followers": 2149,
      "public_repos": 97,
      "public_contributions": 2499,
      "total_contributions": 4962,
      "bio": "Javascript developer, instructor.",
      "company": null,
      "location": "Istanbul, Turkey",
      "twitter": "mehmeteseven",
      "blog": "mehmetseven.net"
    },
    {
      "rank": 15,
      "username": "eser",
      "name": "Eser Ozvataf",
      "avatar": "https://avatars.githubusercontent.com/u/866558?v=4",
      "profile_url": "https://github.com/eser",
      "followers": 2136,
      "public_repos": 200,
      "public_contributions": 1107,
      "total_contributions": 1832,
      "bio": "Founder @acikyazilim • Streaming @ eser.live • Open Source, DevRel, DevOps and Agile Evangelist • Generalist",
      "company": "@acikyazilimagi ",
      "location": "Istanbul, Turkey",
      "twitter": "eser",
      "blog": "https://eser.live/"
    },
    {
      "rank": 16,
      "username": "buraksocial",
      "name": "Burâk",
      "avatar": "https://avatars.githubusercontent.com/u/215418076?v=4",
      "profile_url": "https://github.com/buraksocial",
      "followers": 1862,
      "public_repos": 17,
      "public_contributions": 10513,
      "total_contributions": 10513,
      "bio": "Freelancer.",
      "company": null,
      "location": "Izmir, Turkey",
      "twitter": null,
      "blog": "burakdogan.vercel.app"
    },
    {
      "rank": 17,
      "username": "vigo",
      "name": "Uğur Özyılmazel",
      "avatar": "https://avatars.githubusercontent.com/u/82952?v=4",
      "profile_url": "https://github.com/vigo",
      "followers": 1780,
      "public_repos": 157,
      "public_contributions": 2475,
      "total_contributions": 4349,
      "bio": "Computer programmer with over 30 years of experience who loves #golang #python #ruby and #bash.",
      "company": "@sipay-tr @vbyazilim @bilusteknoloji",
      "location": "Istanbul, Turkey",
      "twitter": null,
      "blog": "https://vigo.io"
    },
    {
      "rank": 18,
      "username": "hasanyalsiz",
      "name": "HASAN YALSIZ",
      "avatar": "https://avatars.githubusercontent.com/u/132101909?v=4",
      "profile_url": "https://github.com/hasanyalsiz",
      "followers": 1778,
      "public_repos": 53,
      "public_contributions": 3,
      "total_contributions": 4,
      "bio": "Software Developer || Front-End Developer || React Developer || Figma",
      "company": "Junius Tech",
      "location": "Turkey",
      "twitter": null,
      "blog": "hasanyalsiz.com"
    },
    {
      "rank": 19,
      "username": "hmert",
      "name": "Hüseyin Mert",
      "avatar": "https://avatars.githubusercontent.com/u/182906?v=4",
      "profile_url": "https://github.com/hmert",
      "followers": 1715,
      "public_repos": 35,
      "public_contributions": 2684,
      "total_contributions": 5055,
      "bio": "building @tapsilat  @monopayments",
      "company": "@tapsilat",
      "location": "Istanbul, Turkey",
      "twitter": "hmert",
      "blog": "http://hmert.com"
    },
    {
      "rank": 20,
      "username": "lemiorhan",
      "name": "Lemi Orhan Ergin",
      "avatar": "https://avatars.githubusercontent.com/u/1199195?v=4",
      "profile_url": "https://github.com/lemiorhan",
      "followers": 1518,
      "public_repos": 26,
      "public_contributions": 300,
      "total_contributions": 572,
      "bio": "Software Crafter,\r\nCo-Founder of @craftgate,\r\nFounder of @scturkey community",
      "company": "Craftbase @craftgate ",
      "location": "Istanbul, Turkey",
      "twitter": "lemiorhan",
      "blog": "lemiorhanergin.com"
    },
    {
      "rank": 21,
      "username": "mstrYoda",
      "name": "Emre Savcı",
      "avatar": "https://avatars.githubusercontent.com/u/12763626?v=4",
      "profile_url": "https://github.com/mstrYoda",
      "followers": 1513,
      "public_repos": 111,
      "public_contributions": 355,
      "total_contributions": 626,
      "bio": "Tech. Lead @Trendyol | K8S <3 | Loves Golang\r\n| Contributions: [docker-shell, awesome-istio, awesome-dapr, @gofiber, @swaggo, kustomize, gocb]",
      "company": "Trendyol",
      "location": "Turkey",
      "twitter": "mstrYoda_",
      "blog": "https://medium.com/@mstrYoda"
    },
    {
      "rank": 22,
      "username": "primefaces",
      "name": "PrimeTek",
      "avatar": "https://avatars.githubusercontent.com/u/3494069?v=4",
      "profile_url": "https://github.com/primefaces",
      "followers": 1509,
      "public_repos": 46,
      "public_contributions": 0,
      "total_contributions": 0,
      "bio": null,
      "company": null,
      "location": "Turkey",
      "twitter": "primefaces",
      "blog": "https://www.primefaces.org"
    },
    {
      "rank": 23,
      "username": "omermertkaya",
      "name": "Ömer Mert KAYA",
      "avatar": "https://avatars.githubusercontent.com/u/10751047?v=4",
      "profile_url": "https://github.com/omermertkaya",
      "followers": 1487,
      "public_repos": 20,
      "public_contributions": 51,
      "total_contributions": 51,
      "bio": null,
      "company": null,
      "location": "Ankara, Turkey",
      "twitter": null,
      "blog": "https://omermertkaya.github.io"
    },
    {
      "rank": 24,
      "username": "tareq1988",
      "name": "Tareq Hasan",
      "avatar": "https://avatars.githubusercontent.com/u/153669?v=4",
      "profile_url": "https://github.com/tareq1988",
      "followers": 1442,
      "public_repos": 105,
      "public_contributions": 429,
      "total_contributions": 788,
      "bio": "Dreamer, Entrepreneur, Introvert, Geek. Founder & CTO of @weDevsOfficial. Building products w/ PHP, WordPress, Laravel, Vue & React. @wp-erp @Appsero @weMail",
      "company": "@weDevsOfficial",
      "location": "Istanbul, Turkey",
      "twitter": "tareq_cse",
      "blog": "https://tareq.co"
    },
    {
      "rank": 25,
      "username": "Furkan-Gulsen",
      "name": "Furkan Gulsen",
      "avatar": "https://avatars.githubusercontent.com/u/41703336?v=4",
      "profile_url": "https://github.com/Furkan-Gulsen",
      "followers": 1361,
      "public_repos": 57,
      "public_contributions": 81,
      "total_contributions": 129,
      "bio": "Software Engineer",
      "company": null,
      "location": "Turkey",
      "twitter": "furkangulsenn",
      "blog": "http://furkangulsen.com"
    }
  ],
  "users_by_public_contributions": [
    {
      "rank": 8,
      "username": "themiralay",
      "name": "Enes Can Işık",
      "avatar": "https://avatars.githubusercontent.com/u/53035239?v=4",
      "profile_url": "https://github.com/themiralay",
      "followers": 3129,
      "public_repos": 47,
      "public_contributions": 105899,
      "total_contributions": 106224,
      "bio": "Back-End Engineer / \r\nCrawler Expert /\r\nWeb3 Dev /\r\nAlgo-Trade Dev /",
      "company": "0x0e0.eth",
      "location": "Turkey",
      "twitter": null,
      "blog": "bulldicator.com"
    },
    {
      "rank": 16,
      "username": "buraksocial",
      "name": "Burâk",
      "avatar": "https://avatars.githubusercontent.com/u/215418076?v=4",
      "profile_url": "https://github.com/buraksocial",
      "followers": 1862,
      "public_repos": 17,
      "public_contributions": 10513,
      "total_contributions": 10513,
      "bio": "Freelancer.",
      "company": null,
      "location": "Izmir, Turkey",
      "twitter": null,
      "blog": "burakdogan.vercel.app"
    },
    {
      "rank": 7,
      "username": "orhun",
      "name": "Orhun Parmaksız",
      "avatar": "https://avatars.githubusercontent.com/u/24392180?v=4",
      "profile_url": "https://github.com/orhun",
      "followers": 4094,
      "public_repos": 497,
      "public_contributions": 4401,
      "total_contributions": 4443,
      "bio": "Terminal Chef at @ratatui |\r\n\r\nMaintainer at @archlinux btw  ",
      "company": "@ratatui | @archlinux",
      "location": "Ankara, Turkey",
      "twitter": null,
      "blog": "orhun.dev"
    },
    {
      "rank": 6,
      "username": "tayfunerbilen",
      "name": "Tayfun Erbilen",
      "avatar": "https://avatars.githubusercontent.com/u/2500557?v=4",
      "profile_url": "https://github.com/tayfunerbilen",
      "followers": 4193,
      "public_repos": 161,
      "public_contributions": 3354,
      "total_contributions": 6697,
      "bio": "It's all about dreams",
      "company": null,
      "location": "Eskişehir, Turkey",
      "twitter": null,
      "blog": "tayfun.net"
    },
    {
      "rank": 19,
      "username": "hmert",
      "name": "Hüseyin Mert",
      "avatar": "https://avatars.githubusercontent.com/u/182906?v=4",
      "profile_url": "https://github.com/hmert",
      "followers": 1715,
      "public_repos": 35,
      "public_contributions": 2684,
      "total_contributions": 5055,
      "bio": "building @tapsilat  @monopayments",
      "company": "@tapsilat",
      "location": "Istanbul, Turkey",
      "twitter": "hmert",
      "blog": "http://hmert.com"
    },
    {
      "rank": 2,
      "username": "f",
      "name": "Fatih Kadir Akın",
      "avatar": "https://avatars.githubusercontent.com/u/196477?v=4",
      "profile_url": "https://github.com/f",
      "followers": 9948,
      "public_repos": 264,
      "public_contributions": 2602,
      "total_contributions": 4324,
      "bio": "Building prompts.chat — JavaScript Developer. Ruby Lover. Author. — @GitHub Star.",
      "company": "@Teknasyon ",
      "location": "Istanbul, Turkey",
      "twitter": "fkadev",
      "blog": "http://fka.dev"
    },
    {
      "rank": 14,
      "username": "meseven",
      "name": "Mehmet Seven",
      "avatar": "https://avatars.githubusercontent.com/u/1716620?v=4",
      "profile_url": "https://github.com/meseven",
      "followers": 2149,
      "public_repos": 97,
      "public_contributions": 2499,
      "total_contributions": 4962,
      "bio": "Javascript developer, instructor.",
      "company": null,
      "location": "Istanbul, Turkey",
      "twitter": "mehmeteseven",
      "blog": "mehmetseven.net"
    },
    {
      "rank": 17,
      "username": "vigo",
      "name": "Uğur Özyılmazel",
      "avatar": "https://avatars.githubusercontent.com/u/82952?v=4",
      "profile_url": "https://github.com/vigo",
      "followers": 1780,
      "public_repos": 157,
      "public_contributions": 2475,
      "total_contributions": 4349,
      "bio": "Computer programmer with over 30 years of experience who loves #golang #python #ruby and #bash.",
      "company": "@sipay-tr @vbyazilim @bilusteknoloji",
      "location": "Istanbul, Turkey",
      "twitter": null,
      "blog": "https://vigo.io"
    },
    {
      "rank": 3,
      "username": "helallao",
      "name": "Ali Yaşar",
      "avatar": "https://avatars.githubusercontent.com/u/78656003?v=4",
      "profile_url": "https://github.com/helallao",
      "followers": 8172,
      "public_repos": 1,
      "public_contributions": 1612,
      "total_contributions": 3138,
      "bio": null,
      "company": "@Metakorteks",
      "location": "Adana, Turkey",
      "twitter": null,
      "blog": "https://metakorteks.com/"
    },
    {
      "rank": 13,
      "username": "buraksenyurt",
      "name": "Burak Selim Senyurt",
      "avatar": "https://avatars.githubusercontent.com/u/2705782?v=4",
      "profile_url": "https://github.com/buraksenyurt",
      "followers": 2372,
      "public_repos": 103,
      "public_contributions": 1476,
      "total_contributions": 1476,
      "bio": "Matematik Mühendisi, MBAci, eski MVP, blogger, @nedirtv editörü. Turuncu sakallı bir yazılım geliştirici.",
      "company": "@DogusTeknoloji",
      "location": "Turkey",
      "twitter": null,
      "blog": "https://www.buraksenyurt.com"
    },
    {
      "rank": 11,
      "username": "hikalkan",
      "name": "Halil İbrahim Kalkan",
      "avatar": "https://avatars.githubusercontent.com/u/1210527?v=4",
      "profile_url": "https://github.com/hikalkan",
      "followers": 2770,
      "public_repos": 34,
      "public_contributions": 1165,
      "total_contributions": 1929,
      "bio": "Sofware architect, developer and entrepreneur (@volosoft).",
      "company": "Volosoft",
      "location": "Istanbul, Turkey",
      "twitter": "hibrahimkalkan",
      "blog": "https://halilibrahimkalkan.com"
    },
    {
      "rank": 15,
      "username": "eser",
      "name": "Eser Ozvataf",
      "avatar": "https://avatars.githubusercontent.com/u/866558?v=4",
      "profile_url": "https://github.com/eser",
      "followers": 2136,
      "public_repos": 200,
      "public_contributions": 1107,
      "total_contributions": 1832,
      "bio": "Founder @acikyazilim • Streaming @ eser.live • Open Source, DevRel, DevOps and Agile Evangelist • Generalist",
      "company": "@acikyazilimagi ",
      "location": "Istanbul, Turkey",
      "twitter": "eser",
      "blog": "https://eser.live/"
    },
    {
      "rank": 12,
      "username": "cobanov",
      "name": "Mert Cobanov",
      "avatar": "https://avatars.githubusercontent.com/u/29142615?v=4",
      "profile_url": "https://github.com/cobanov",
      "followers": 2485,
      "public_repos": 63,
      "public_contributions": 567,
      "total_contributions": 974,
      "bio": "Senior AI Engineer & Generative Artist",
      "company": "@RefikAnadolStudio ",
      "location": "Turkey",
      "twitter": "mertcobanov",
      "blog": "cobanov.dev"
    },
    {
      "rank": 4,
      "username": "seckinyasar",
      "name": "Seckin Yasar",
      "avatar": "https://avatars.githubusercontent.com/u/86570205?v=4",
      "profile_url": "https://github.com/seckinyasar",
      "followers": 7205,
      "public_repos": 3,
      "public_contributions": 563,
      "total_contributions": 1051,
      "bio": null,
      "company": "@Metakorteks",
      "location": "Turkey",
      "twitter": null,
      "blog": "https://metakorteks.com/"
    },
    {
      "rank": 24,
      "username": "tareq1988",
      "name": "Tareq Hasan",
      "avatar": "https://avatars.githubusercontent.com/u/153669?v=4",
      "profile_url": "https://github.com/tareq1988",
      "followers": 1442,
      "public_repos": 105,
      "public_contributions": 429,
      "total_contributions": 788,
      "bio": "Dreamer, Entrepreneur, Introvert, Geek. Founder & CTO of @weDevsOfficial. Building products w/ PHP, WordPress, Laravel, Vue & React. @wp-erp @Appsero @weMail",
      "company": "@weDevsOfficial",
      "location": "Istanbul, Turkey",
      "twitter": "tareq_cse",
      "blog": "https://tareq.co"
    },
    {
      "rank": 21,
      "username": "mstrYoda",
      "name": "Emre Savcı",
      "avatar": "https://avatars.githubusercontent.com/u/12763626?v=4",
      "profile_url": "https://github.com/mstrYoda",
      "followers": 1513,
      "public_repos": 111,
      "public_contributions": 355,
      "total_contributions": 626,
      "bio": "Tech. Lead @Trendyol | K8S <3 | Loves Golang\r\n| Contributions: [docker-shell, awesome-istio, awesome-dapr, @gofiber, @swaggo, kustomize, gocb]",
      "company": "Trendyol",
      "location": "Turkey",
      "twitter": "mstrYoda_",
      "blog": "https://medium.com/@mstrYoda"
    },
    {
      "rank": 5,
      "username": "emirkaanozdemr",
      "name": "Emir Kaan Özdemir",
      "avatar": "https://avatars.githubusercontent.com/u/155099794?v=4",
      "profile_url": "https://github.com/emirkaanozdemr",
      "followers": 6033,
      "public_repos": 124,
      "public_contributions": 310,
      "total_contributions": 470,
      "bio": "Data Scientist | Astronomy and Quantum Computing Enthusiast | Founder and Superposition of @Qranscend | Co-Founder of @Lyra-AI-Team | High School Student",
      "company": null,
      "location": "Istanbul, Turkey",
      "twitter": "emirkaanozdemr",
      "blog": ""
    },
    {
      "rank": 20,
      "username": "lemiorhan",
      "name": "Lemi Orhan Ergin",
      "avatar": "https://avatars.githubusercontent.com/u/1199195?v=4",
      "profile_url": "https://github.com/lemiorhan",
      "followers": 1518,
      "public_repos": 26,
      "public_contributions": 300,
      "total_contributions": 572,
      "bio": "Software Crafter,\r\nCo-Founder of @craftgate,\r\nFounder of @scturkey community",
      "company": "Craftbase @craftgate ",
      "location": "Istanbul, Turkey",
      "twitter": "lemiorhan",
      "blog": "lemiorhanergin.com"
    },
    {
      "rank": 25,
      "username": "Furkan-Gulsen",
      "name": "Furkan Gulsen",
      "avatar": "https://avatars.githubusercontent.com/u/41703336?v=4",
      "profile_url": "https://github.com/Furkan-Gulsen",
      "followers": 1361,
      "public_repos": 57,
      "public_contributions": 81,
      "total_contributions": 129,
      "bio": "Software Engineer",
      "company": null,
      "location": "Turkey",
      "twitter": "furkangulsenn",
      "blog": "http://furkangulsen.com"
    },
    {
      "rank": 23,
      "username": "omermertkaya",
      "name": "Ömer Mert KAYA",
      "avatar": "https://avatars.githubusercontent.com/u/10751047?v=4",
      "profile_url": "https://github.com/omermertkaya",
      "followers": 1487,
      "public_repos": 20,
      "public_contributions": 51,
      "total_contributions": 51,
      "bio": null,
      "company": null,
      "location": "Ankara, Turkey",
      "twitter": null,
      "blog": "https://omermertkaya.github.io"
    },
    {
      "rank": 9,
      "username": "borakasmer",
      "name": "Bora KAŞMER",
      "avatar": "https://avatars.githubusercontent.com/u/9459881?v=4",
      "profile_url": "https://github.com/borakasmer",
      "followers": 2914,
      "public_repos": 154,
      "public_contributions": 22,
      "total_contributions": 22,
      "bio": "Bazıları Hayal Eder Bazıları Yapar",
      "company": "KeepnetLabs Cyber Security",
      "location": "Istanbul / Turkey",
      "twitter": "coderbora",
      "blog": "https://borakasmer.com/"
    },
    {
      "rank": 18,
      "username": "hasanyalsiz",
      "name": "HASAN YALSIZ",
      "avatar": "https://avatars.githubusercontent.com/u/132101909?v=4",
      "profile_url": "https://github.com/hasanyalsiz",
      "followers": 1778,
      "public_repos": 53,
      "public_contributions": 3,
      "total_contributions": 4,
      "bio": "Software Developer || Front-End Developer || React Developer || Figma",
      "company": "Junius Tech",
      "location": "Turkey",
      "twitter": null,
      "blog": "hasanyalsiz.com"
    },
    {
      "rank": 1,
      "username": "metatimeofficial",
      "name": "Metatime",
      "avatar": "https://avatars.githubusercontent.com/u/109962392?v=4",
      "profile_url": "https://github.com/metatimeofficial",
      "followers": 18065,
      "public_repos": 2,
      "public_contributions": 0,
      "total_contributions": 0,
      "bio": "The New Standard.",
      "company": "Metatime Technology Inc.",
      "location": "İstanbul, Turkey",
      "twitter": "metatimecom",
      "blog": "https://metatime.com"
    },
    {
      "rank": 10,
      "username": "Omar95-A",
      "name": "Ömer Akrum",
      "avatar": "https://avatars.githubusercontent.com/u/81801245?v=4",
      "profile_url": "https://github.com/Omar95-A",
      "followers": 2797,
      "public_repos": 12,
      "public_contributions": 0,
      "total_contributions": 0,
      "bio": "Software Engineer | Front-End Developer",
      "company": "Self-employed",
      "location": "İstanbul, Turkey",
      "twitter": null,
      "blog": ""
    },
    {
      "rank": 22,
      "username": "primefaces",
      "name": "PrimeTek",
      "avatar": "https://avatars.githubusercontent.com/u/3494069?v=4",
      "profile_url": "https://github.com/primefaces",
      "followers": 1509,
      "public_repos": 46,
      "public_contributions": 0,
      "total_contributions": 0,
      "bio": null,
      "company": null,
      "location": "Turkey",
      "twitter": "primefaces",
      "blog": "https://www.primefaces.org"
    }
  ],
  "users_by_total_contributions": [
    {
      "rank": 8,
      "username": "themiralay",
      "name": "Enes Can Işık",
      "avatar": "https://avatars.githubusercontent.com/u/53035239?v=4",
      "profile_url": "https://github.com/themiralay",
      "followers": 3129,
      "public_repos": 47,
      "public_contributions": 105899,
      "total_contributions": 106224,
      "bio": "Back-End Engineer / \r\nCrawler Expert /\r\nWeb3 Dev /\r\nAlgo-Trade Dev /",
      "company": "0x0e0.eth",
      "location": "Turkey",
      "twitter": null,
      "blog": "bulldicator.com"
    },
    {
      "rank": 16,
      "username": "buraksocial",
      "name": "Burâk",
      "avatar": "https://avatars.githubusercontent.com/u/215418076?v=4",
      "profile_url": "https://github.com/buraksocial",
      "followers": 1862,
      "public_repos": 17,
      "public_contributions": 10513,
      "total_contributions": 10513,
      "bio": "Freelancer.",
      "company": null,
      "location": "Izmir, Turkey",
      "twitter": null,
      "blog": "burakdogan.vercel.app"
    },
    {
      "rank": 6,
      "username": "tayfunerbilen",
      "name": "Tayfun Erbilen",
      "avatar": "https://avatars.githubusercontent.com/u/2500557?v=4",
      "profile_url": "https://github.com/tayfunerbilen",
      "followers": 4193,
      "public_repos": 161,
      "public_contributions": 3354,
      "total_contributions": 6697,
      "bio": "It's all about dreams",
      "company": null,
      "location": "Eskişehir, Turkey",
      "twitter": null,
      "blog": "tayfun.net"
    },
    {
      "rank": 19,
      "username": "hmert",
      "name": "Hüseyin Mert",
      "avatar": "https://avatars.githubusercontent.com/u/182906?v=4",
      "profile_url": "https://github.com/hmert",
      "followers": 1715,
      "public_repos": 35,
      "public_contributions": 2684,
      "total_contributions": 5055,
      "bio": "building @tapsilat  @monopayments",
      "company": "@tapsilat",
      "location": "Istanbul, Turkey",
      "twitter": "hmert",
      "blog": "http://hmert.com"
    },
    {
      "rank": 14,
      "username": "meseven",
      "name": "Mehmet Seven",
      "avatar": "https://avatars.githubusercontent.com/u/1716620?v=4",
      "profile_url": "https://github.com/meseven",
      "followers": 2149,
      "public_repos": 97,
      "public_contributions": 2499,
      "total_contributions": 4962,
      "bio": "Javascript developer, instructor.",
      "company": null,
      "location": "Istanbul, Turkey",
      "twitter": "mehmeteseven",
      "blog": "mehmetseven.net"
    },
    {
      "rank": 7,
      "username": "orhun",
      "name": "Orhun Parmaksız",
      "avatar": "https://avatars.githubusercontent.com/u/24392180?v=4",
      "profile_url": "https://github.com/orhun",
      "followers": 4094,
      "public_repos": 497,
      "public_contributions": 4401,
      "total_contributions": 4443,
      "bio": "Terminal Chef at @ratatui |\r\n\r\nMaintainer at @archlinux btw  ",
      "company": "@ratatui | @archlinux",
      "location": "Ankara, Turkey",
      "twitter": null,
      "blog": "orhun.dev"
    },
    {
      "rank": 17,
      "username": "vigo",
      "name": "Uğur Özyılmazel",
      "avatar": "https://avatars.githubusercontent.com/u/82952?v=4",
      "profile_url": "https://github.com/vigo",
      "followers": 1780,
      "public_repos": 157,
      "public_contributions": 2475,
      "total_contributions": 4349,
      "bio": "Computer programmer with over 30 years of experience who loves #golang #python #ruby and #bash.",
      "company": "@sipay-tr @vbyazilim @bilusteknoloji",
      "location": "Istanbul, Turkey",
      "twitter": null,
      "blog": "https://vigo.io"
    },
    {
      "rank": 2,
      "username": "f",
      "name": "Fatih Kadir Akın",
      "avatar": "https://avatars.githubusercontent.com/u/196477?v=4",
      "profile_url": "https://github.com/f",
      "followers": 9948,
      "public_repos": 264,
      "public_contributions": 2602,
      "total_contributions": 4324,
      "bio": "Building prompts.chat — JavaScript Developer. Ruby Lover. Author. — @GitHub Star.",
      "company": "@Teknasyon ",
      "location": "Istanbul, Turkey",
      "twitter": "fkadev",
      "blog": "http://fka.dev"
    },
    {
      "rank": 3,
      "username": "helallao",
      "name": "Ali Yaşar",
      "avatar": "https://avatars.githubusercontent.com/u/78656003?v=4",
      "profile_url": "https://github.com/helallao",
      "followers": 8172,
      "public_repos": 1,
      "public_contributions": 1612,
      "total_contributions": 3138,
      "bio": null,
      "company": "@Metakorteks",
      "location": "Adana, Turkey",
      "twitter": null,
      "blog": "https://metakorteks.com/"
    },
    {
      "rank": 11,
      "username": "hikalkan",
      "name": "Halil İbrahim Kalkan",
      "avatar": "https://avatars.githubusercontent.com/u/1210527?v=4",
      "profile_url": "https://github.com/hikalkan",
      "followers": 2770,
      "public_repos": 34,
      "public_contributions": 1165,
      "total_contributions": 1929,
      "bio": "Sofware architect, developer and entrepreneur (@volosoft).",
      "company": "Volosoft",
      "location": "Istanbul, Turkey",
      "twitter": "hibrahimkalkan",
      "blog": "https://halilibrahimkalkan.com"
    },
    {
      "rank": 15,
      "username": "eser",
      "name": "Eser Ozvataf",
      "avatar": "https://avatars.githubusercontent.com/u/866558?v=4",
      "profile_url": "https://github.com/eser",
      "followers": 2136,
      "public_repos": 200,
      "public_contributions": 1107,
      "total_contributions": 1832,
      "bio": "Founder @acikyazilim • Streaming @ eser.live • Open Source, DevRel, DevOps and Agile Evangelist • Generalist",
      "company": "@acikyazilimagi ",
      "location": "Istanbul, Turkey",
      "twitter": "eser",
      "blog": "https://eser.live/"
    },
    {
      "rank": 13,
      "username": "buraksenyurt",
      "name": "Burak Selim Senyurt",
      "avatar": "https://avatars.githubusercontent.com/u/2705782?v=4",
      "profile_url": "https://github.com/buraksenyurt",
      "followers": 2372,
      "public_repos": 103,
      "public_contributions": 1476,
      "total_contributions": 1476,
      "bio": "Matematik Mühendisi, MBAci, eski MVP, blogger, @nedirtv editörü. Turuncu sakallı bir yazılım geliştirici.",
      "company": "@DogusTeknoloji",
      "location": "Turkey",
      "twitter": null,
      "blog": "https://www.buraksenyurt.com"
    },
    {
      "rank": 4,
      "username": "seckinyasar",
      "name": "Seckin Yasar",
      "avatar": "https://avatars.githubusercontent.com/u/86570205?v=4",
      "profile_url": "https://github.com/seckinyasar",
      "followers": 7205,
      "public_repos": 3,
      "public_contributions": 563,
      "total_contributions": 1051,
      "bio": null,
      "company": "@Metakorteks",
      "location": "Turkey",
      "twitter": null,
      "blog": "https://metakorteks.com/"
    },
    {
      "rank": 12,
      "username": "cobanov",
      "name": "Mert Cobanov",
      "avatar": "https://avatars.githubusercontent.com/u/29142615?v=4",
      "profile_url": "https://github.com/cobanov",
      "followers": 2485,
      "public_repos": 63,
      "public_contributions": 567,
      "total_contributions": 974,
      "bio": "Senior AI Engineer & Generative Artist",
      "company": "@RefikAnadolStudio ",
      "location": "Turkey",
      "twitter": "mertcobanov",
      "blog": "cobanov.dev"
    },
    {
      "rank": 24,
      "username": "tareq1988",
      "name": "Tareq Hasan",
      "avatar": "https://avatars.githubusercontent.com/u/153669?v=4",
      "profile_url": "https://github.com/tareq1988",
      "followers": 1442,
      "public_repos": 105,
      "public_contributions": 429,
      "total_contributions": 788,
      "bio": "Dreamer, Entrepreneur, Introvert, Geek. Founder & CTO of @weDevsOfficial. Building products w/ PHP, WordPress, Laravel, Vue & React. @wp-erp @Appsero @weMail",
      "company": "@weDevsOfficial",
      "location": "Istanbul, Turkey",
      "twitter": "tareq_cse",
      "blog": "https://tareq.co"
    },
    {
      "rank": 21,
      "username": "mstrYoda",
      "name": "Emre Savcı",
      "avatar": "https://avatars.githubusercontent.com/u/12763626?v=4",
      "profile_url": "https://github.com/mstrYoda",
      "followers": 1513,
      "public_repos": 111,
      "public_contributions": 355,
      "total_contributions": 626,
      "bio": "Tech. Lead @Trendyol | K8S <3 | Loves Golang\r\n| Contributions: [docker-shell, awesome-istio, awesome-dapr, @gofiber, @swaggo, kustomize, gocb]",
      "company": "Trendyol",
      "location": "Turkey",
      "twitter": "mstrYoda_",
      "blog": "https://medium.com/@mstrYoda"
    },
    {
      "rank": 20,
      "username": "lemiorhan",
      "name": "Lemi Orhan Ergin",
      "avatar": "https://avatars.githubusercontent.com/u/1199195?v=4",
      "profile_url": "https://github.com/lemiorhan",
      "followers": 1518,
      "public_repos": 26,
      "public_contributions": 300,
      "total_contributions": 572,
      "bio": "Software Crafter,\r\nCo-Founder of @craftgate,\r\nFounder of @scturkey community",
      "company": "Craftbase @craftgate ",
      "location": "Istanbul, Turkey",
      "twitter": "lemiorhan",
      "blog": "lemiorhanergin.com"
    },
    {
      "rank": 5,
      "username": "emirkaanozdemr",
      "name": "Emir Kaan Özdemir",
      "avatar": "https://avatars.githubusercontent.com/u/155099794?v=4",
      "profile_url": "https://github.com/emirkaanozdemr",
      "followers": 6033,
      "public_repos": 124,
      "public_contributions": 310,
      "total_contributions": 470,
      "bio": "Data Scientist | Astronomy and Quantum Computing Enthusiast | Founder and Superposition of @Qranscend | Co-Founder of @Lyra-AI-Team | High School Student",
      "company": null,
      "location": "Istanbul, Turkey",
      "twitter": "emirkaanozdemr",
      "blog": ""
    },
    {
      "rank": 25,
      "username": "Furkan-Gulsen",
      "name": "Furkan Gulsen",
      "avatar": "https://avatars.githubusercontent.com/u/41703336?v=4",
      "profile_url": "https://github.com/Furkan-Gulsen",
      "followers": 1361,
      "public_repos": 57,
      "public_contributions": 81,
      "total_contributions": 129,
      "bio": "Software Engineer",
      "company": null,
      "location": "Turkey",
      "twitter": "furkangulsenn",
      "blog": "http://furkangulsen.com"
    },
    {
      "rank": 23,
      "username": "omermertkaya",
      "name": "Ömer Mert KAYA",
      "avatar": "https://avatars.githubusercontent.com/u/10751047?v=4",
      "profile_url": "https://github.com/omermertkaya",
      "followers": 1487,
      "public_repos": 20,
      "public_contributions": 51,
      "total_contributions": 51,
      "bio": null,
      "company": null,
      "location": "Ankara, Turkey",
      "twitter": null,
      "blog": "https://omermertkaya.github.io"
    },
    {
      "rank": 9,
      "username": "borakasmer",
      "name": "Bora KAŞMER",
      "avatar": "https://avatars.githubusercontent.com/u/9459881?v=4",
      "profile_url": "https://github.com/borakasmer",
      "followers": 2914,
      "public_repos": 154,
      "public_contributions": 22,
      "total_contributions": 22,
      "bio": "Bazıları Hayal Eder Bazıları Yapar",
      "company": "KeepnetLabs Cyber Security",
      "location": "Istanbul / Turkey",
      "twitter": "coderbora",
      "blog": "https://borakasmer.com/"
    },
    {
      "rank": 18,
      "username": "hasanyalsiz",
      "name": "HASAN YALSIZ",
      "avatar": "https://avatars.githubusercontent.com/u/132101909?v=4",
      "profile_url": "https://github.com/hasanyalsiz",
      "followers": 1778,
      "public_repos": 53,
      "public_contributions": 3,
      "total_contributions": 4,
      "bio": "Software Developer || Front-End Developer || React Developer || Figma",
      "company": "Junius Tech",
      "location": "Turkey",
      "twitter": null,
      "blog": "hasanyalsiz.com"
    },
    {
      "rank": 1,
      "username": "metatimeofficial",
      "name": "Metatime",
      "avatar": "https://avatars.githubusercontent.com/u/109962392?v=4",
      "profile_url": "https://github.com/metatimeofficial",
      "followers": 18065,
      "public_repos": 2,
      "public_contributions": 0,
      "total_contributions": 0,
      "bio": "The New Standard.",
      "company": "Metatime Technology Inc.",
      "location": "İstanbul, Turkey",
      "twitter": "metatimecom",
      "blog": "https://metatime.com"
    },
    {
      "rank": 10,
      "username": "Omar95-A",
      "name": "Ömer Akrum",
      "avatar": "https://avatars.githubusercontent.com/u/81801245?v=4",
      "profile_url": "https://github.com/Omar95-A",
      "followers": 2797,
      "public_repos": 12,
      "public_contributions": 0,
      "total_contributions": 0,
      "bio": "Software Engineer | Front-End Developer",
      "company": "Self-employed",
      "location": "İstanbul, Turkey",
      "twitter": null,
      "blog": ""
    },
    {
      "rank": 22,
      "username": "primefaces",
      "name": "PrimeTek",
      "avatar": "https://avatars.githubusercontent.com/u/3494069?v=4",
      "profile_url": "https://github.com/primefaces",
      "followers": 1509,
      "public_repos": 46,
      "public_contributions": 0,
      "total_contributions": 0,
      "bio": null,
      "company": null,
      "location": "Turkey",
      "twitter": "primefaces",
      "blog": "https://www.primefaces.org"
    }
  ]
}