{"ranking":[{"name":"Afghanistan","value":101474},{"name":"Albania","value":42960},{"name":"Algeria","value":121125},{"name":"Andorra","value":12103},{"name":"Angola","value":68151},{"name":"Argentina","value":185005},{"name":"Armenia","value":84784},{"name":"Australia","value":389541},{"name":"Austria","value":316970},{"name":"Azerbaijan","value":133763},{"name":"Bahrain","value":25437},{"name":"Bangladesh","value":173334},{"name":"Belarus","value":92520},{"name":"Belgium","value":326146},{"name":"Benin","value":56616},{"name":"Bhutan","value":10332},{"name":"Bolivia","value":77013},{"name":"Bosnia and Herz.","value":372},{"name":"Botswana","value":12748},{"name":"Brazil","value":238257},{"name":"Bulgaria","value":206628},{"name":"Burkina Faso","value":8693},{"name":"Burundi","value":14573},{"name":"Cambodia","value":70362},{"name":"Cameroon","value":115921},{"name":"Canada","value":410005},{"name":"Chad","value":6073},{"name":"Chile","value":131146},{"name":"China","value":332452},{"name":"Colombia","value":141049},{"name":"Congo","value":27140},{"name":"Croatia","value":137356},{"name":"Cuba","value":96998},{"name":"Cyprus","value":90366},{"name":"Czechia","value":314373},{"name":"Denmark","value":271844},{"name":"Dominican Rep.","value":42396},{"name":"Ecuador","value":96203},{"name":"Egypt","value":215055},{"name":"El Salvador","value":52093},{"name":"Estonia","value":114369},{"name":"Ethiopia","value":255923},{"name":"Finland","value":250898},{"name":"France","value":531585},{"name":"Georgia","value":141969},{"name":"Germany","value":621279},{"name":"Ghana","value":185915},{"name":"Greece","value":168195},{"name":"Guatemala","value":79522},{"name":"Honduras","value":34022},{"name":"Hong Kong","value":184618},{"name":"Hungary","value":207415},{"name":"Iceland","value":62288},{"name":"India","value":239374},{"name":"Indonesia","value":344545},{"name":"Iran","value":244491},{"name":"Iraq","value":55095},{"name":"Ireland","value":176211},{"name":"Israel","value":221367},{"name":"Italy","value":368031},{"name":"Jamaica","value":66184},{"name":"Japan","value":502887},{"name":"Jordan","value":53422},{"name":"Kazakhstan","value":80854},{"name":"Kenya","value":335341},{"name":"Kuwait","value":16424},{"name":"Laos","value":9514},{"name":"Latvia","value":70364},{"name":"Lithuania","value":90290},{"name":"Luxembourg","value":66532},{"name":"Madagascar","value":114389},{"name":"Malawi","value":39207},{"name":"Malaysia","value":134867},{"name":"Maldives","value":10584},{"name":"Mali","value":10289},{"name":"Malta","value":41582},{"name":"Mauritania","value":5495},{"name":"Mauritius","value":30895},{"name":"Mexico","value":164388},{"name":"Moldova","value":50615},{"name":"Mongolia","value":29028},{"name":"Montenegro","value":47371},{"name":"Morocco","value":194636},{"name":"Mozambique","value":28092},{"name":"Myanmar","value":93498},{"name":"Namibia","value":12997},{"name":"Nepal","value":188789},{"name":"Netherlands","value":429072},{"name":"New Zealand","value":167429},{"name":"Nicaragua","value":102550},{"name":"Nigeria","value":168396},{"name":"Norway","value":265290},{"name":"Oman","value":30490},{"name":"Pakistan","value":171131},{"name":"Palestine","value":64459},{"name":"Panama","value":31289},{"name":"Paraguay","value":58350},{"name":"Peru","value":101017},{"name":"Philippines","value":316176},{"name":"Poland","value":332514},{"name":"Portugal","value":241220},{"name":"Qatar","value":28035},{"name":"Romania","value":186086},{"name":"Russia","value":222323},{"name":"Rwanda","value":209319},{"name":"San Marino","value":1739},{"name":"Saudi Arabia","value":36158},{"name":"Senegal","value":56283},{"name":"Serbia","value":146091},{"name":"Sierra Leone","value":8765},{"name":"Singapore","value":198664},{"name":"Slovakia","value":122229},{"name":"Slovenia","value":116430},{"name":"South Africa","value":150476},{"name":"South Korea","value":289705},{"name":"Spain","value":408236},{"name":"Sri Lanka","value":199993},{"name":"Sudan","value":35941},{"name":"Sweden","value":322196},{"name":"Switzerland","value":407065},{"name":"Syria","value":45536},{"name":"Taiwan","value":308330},{"name":"Tanzania","value":85806},{"name":"Thailand","value":185166},{"name":"Tunisia","value":131532},{"name":"Turkey","value":163147},{"name":"Uganda","value":131660},{"name":"Ukraine","value":194540},{"name":"United Arab Emirates","value":161},{"name":"United Kingdom","value":423839},{"name":"United States of America","value":375544},{"name":"Uruguay","value":90397},{"name":"Uzbekistan","value":134463},{"name":"Venezuela","value":110011},{"name":"Vietnam","value":214815},{"name":"Yemen","value":44822},{"name":"Zambia","value":39139},{"name":"Zambia","value":57520}]}
