{"ranking":[{"name":"Afghanistan","value":109513},{"name":"Albania","value":40245},{"name":"Algeria","value":119630},{"name":"Andorra","value":11530},{"name":"Angola","value":64538},{"name":"Argentina","value":181709},{"name":"Armenia","value":90734},{"name":"Australia","value":384263},{"name":"Austria","value":317600},{"name":"Azerbaijan","value":133289},{"name":"Bahrain","value":19422},{"name":"Bangladesh","value":192388},{"name":"Belarus","value":95292},{"name":"Belgium","value":313891},{"name":"Benin","value":58710},{"name":"Bhutan","value":10909},{"name":"Bolivia","value":69900},{"name":"Bosnia and Herz.","value":372},{"name":"Botswana","value":15809},{"name":"Brazil","value":238257},{"name":"Bulgaria","value":211871},{"name":"Burkina Faso","value":4498},{"name":"Burundi","value":14393},{"name":"Cambodia","value":61881},{"name":"Cameroon","value":119843},{"name":"Canada","value":385566},{"name":"Chad","value":6053},{"name":"Chile","value":140432},{"name":"China","value":326840},{"name":"Colombia","value":138462},{"name":"Congo","value":28315},{"name":"Croatia","value":137076},{"name":"Cuba","value":95611},{"name":"Cyprus","value":91354},{"name":"Czechia","value":316202},{"name":"Denmark","value":267229},{"name":"Dominican Rep.","value":40539},{"name":"Ecuador","value":99204},{"name":"Egypt","value":232696},{"name":"El Salvador","value":54849},{"name":"Estonia","value":115650},{"name":"Ethiopia","value":269373},{"name":"Finland","value":249082},{"name":"France","value":536946},{"name":"Georgia","value":144262},{"name":"Germany","value":622492},{"name":"Ghana","value":222015},{"name":"Greece","value":161763},{"name":"Guatemala","value":75151},{"name":"Honduras","value":36263},{"name":"Hong Kong","value":188412},{"name":"Hungary","value":203014},{"name":"Iceland","value":61728},{"name":"India","value":251693},{"name":"Indonesia","value":362126},{"name":"Iran","value":238328},{"name":"Iraq","value":56379},{"name":"Ireland","value":173797},{"name":"Israel","value":215453},{"name":"Italy","value":368786},{"name":"Jamaica","value":63793},{"name":"Japan","value":506179},{"name":"Jordan","value":51448},{"name":"Kazakhstan","value":78084},{"name":"Kenya","value":358987},{"name":"Kuwait","value":16890},{"name":"Laos","value":7501},{"name":"Latvia","value":64289},{"name":"Lithuania","value":87593},{"name":"Luxembourg","value":63033},{"name":"Madagascar","value":115978},{"name":"Malawi","value":38331},{"name":"Malaysia","value":145451},{"name":"Maldives","value":10027},{"name":"Mali","value":12391},{"name":"Malta","value":37122},{"name":"Mauritania","value":5434},{"name":"Mauritius","value":29915},{"name":"Mexico","value":170192},{"name":"Moldova","value":46309},{"name":"Mongolia","value":36787},{"name":"Montenegro","value":49883},{"name":"Morocco","value":229793},{"name":"Mozambique","value":32548},{"name":"Myanmar","value":87530},{"name":"Namibia","value":15765},{"name":"Nepal","value":166315},{"name":"Netherlands","value":431475},{"name":"New Zealand","value":162548},{"name":"Nicaragua","value":99855},{"name":"Nigeria","value":193442},{"name":"Norway","value":262420},{"name":"Oman","value":27188},{"name":"Pakistan","value":177825},{"name":"Palestine","value":73470},{"name":"Panama","value":28973},{"name":"Paraguay","value":58172},{"name":"Peru","value":102085},{"name":"Philippines","value":339975},{"name":"Poland","value":342849},{"name":"Portugal","value":251351},{"name":"Qatar","value":28979},{"name":"Romania","value":170917},{"name":"Russia","value":246092},{"name":"Rwanda","value":209390},{"name":"San Marino","value":1957},{"name":"Saudi Arabia","value":39106},{"name":"Senegal","value":55900},{"name":"Serbia","value":154038},{"name":"Sierra Leone","value":6417},{"name":"Singapore","value":205633},{"name":"Slovakia","value":125913},{"name":"Slovenia","value":117126},{"name":"South Africa","value":149414},{"name":"South Korea","value":307586},{"name":"Spain","value":387454},{"name":"Sri Lanka","value":185535},{"name":"Sudan","value":39400},{"name":"Sweden","value":317058},{"name":"Switzerland","value":401479},{"name":"Syria","value":39748},{"name":"Taiwan","value":285123},{"name":"Tanzania","value":87495},{"name":"Thailand","value":196952},{"name":"Tunisia","value":119273},{"name":"Turkey","value":165691},{"name":"Uganda","value":152281},{"name":"Ukraine","value":198441},{"name":"United Arab Emirates","value":207},{"name":"United Kingdom","value":398821},{"name":"United States of America","value":367600},{"name":"Uruguay","value":101373},{"name":"Uzbekistan","value":139415},{"name":"Venezuela","value":118173},{"name":"Vietnam","value":223834},{"name":"Yemen","value":52544},{"name":"Zambia","value":42629},{"name":"Zambia","value":50558}]}
