{"ranking":[{"name":"Afghanistan","value":107860},{"name":"Albania","value":33592},{"name":"Algeria","value":118176},{"name":"Andorra","value":17211},{"name":"Angola","value":71559},{"name":"Argentina","value":189575},{"name":"Armenia","value":100695},{"name":"Australia","value":357231},{"name":"Austria","value":315598},{"name":"Azerbaijan","value":112313},{"name":"Bahrain","value":15231},{"name":"Bangladesh","value":239901},{"name":"Belarus","value":98323},{"name":"Belgium","value":320615},{"name":"Benin","value":63428},{"name":"Bhutan","value":11043},{"name":"Bolivia","value":65238},{"name":"Bosnia and Herz.","value":372},{"name":"Botswana","value":20222},{"name":"Brazil","value":245860},{"name":"Bulgaria","value":229058},{"name":"Burkina Faso","value":6563},{"name":"Burundi","value":17974},{"name":"Cambodia","value":58855},{"name":"Cameroon","value":144614},{"name":"Canada","value":407786},{"name":"Chad","value":2914},{"name":"Chile","value":142492},{"name":"China","value":348174},{"name":"Colombia","value":156536},{"name":"Congo","value":33802},{"name":"Croatia","value":137918},{"name":"Cuba","value":64299},{"name":"Cyprus","value":89371},{"name":"Czechia","value":318969},{"name":"Denmark","value":275173},{"name":"Dominican Rep.","value":37510},{"name":"Ecuador","value":127532},{"name":"Egypt","value":242796},{"name":"El Salvador","value":49437},{"name":"Estonia","value":118977},{"name":"Ethiopia","value":359403},{"name":"Finland","value":284858},{"name":"France","value":528239},{"name":"Georgia","value":150959},{"name":"Germany","value":601409},{"name":"Ghana","value":301169},{"name":"Greece","value":170282},{"name":"Guatemala","value":85188},{"name":"Honduras","value":43707},{"name":"Hong Kong","value":188941},{"name":"Hungary","value":204867},{"name":"Iceland","value":58195},{"name":"India","value":307566},{"name":"Indonesia","value":333826},{"name":"Iran","value":221635},{"name":"Iraq","value":64243},{"name":"Ireland","value":167861},{"name":"Israel","value":241742},{"name":"Italy","value":370535},{"name":"Jamaica","value":53759},{"name":"Japan","value":518722},{"name":"Jordan","value":71866},{"name":"Kazakhstan","value":81790},{"name":"Kenya","value":457357},{"name":"Kuwait","value":15997},{"name":"Laos","value":6019},{"name":"Latvia","value":71308},{"name":"Lithuania","value":87267},{"name":"Luxembourg","value":61692},{"name":"Madagascar","value":77402},{"name":"Malawi","value":45079},{"name":"Malaysia","value":145143},{"name":"Maldives","value":8769},{"name":"Mali","value":13979},{"name":"Malta","value":41614},{"name":"Mauritania","value":4400},{"name":"Mauritius","value":30115},{"name":"Mexico","value":159985},{"name":"Moldova","value":53724},{"name":"Mongolia","value":40564},{"name":"Montenegro","value":54986},{"name":"Morocco","value":232975},{"name":"Mozambique","value":50773},{"name":"Myanmar","value":95730},{"name":"Namibia","value":18526},{"name":"Nepal","value":168421},{"name":"Netherlands","value":445372},{"name":"New Zealand","value":149981},{"name":"Nicaragua","value":100336},{"name":"Nigeria","value":301059},{"name":"Norway","value":299841},{"name":"Oman","value":21140},{"name":"Pakistan","value":208868},{"name":"Palestine","value":102670},{"name":"Panama","value":30606},{"name":"Paraguay","value":53849},{"name":"Peru","value":112660},{"name":"Philippines","value":254588},{"name":"Poland","value":359907},{"name":"Portugal","value":265516},{"name":"Qatar","value":20371},{"name":"Romania","value":193659},{"name":"Russia","value":233528},{"name":"Rwanda","value":246011},{"name":"San Marino","value":2382},{"name":"Saudi Arabia","value":39676},{"name":"Senegal","value":48142},{"name":"Serbia","value":161700},{"name":"Sierra Leone","value":7406},{"name":"Singapore","value":233182},{"name":"Slovakia","value":135288},{"name":"Slovenia","value":109164},{"name":"South Africa","value":144030},{"name":"South Korea","value":306113},{"name":"Spain","value":397101},{"name":"Sri Lanka","value":156241},{"name":"Sudan","value":42200},{"name":"Sweden","value":306816},{"name":"Switzerland","value":356331},{"name":"Syria","value":33808},{"name":"Taiwan","value":310325},{"name":"Tanzania","value":116553},{"name":"Thailand","value":220953},{"name":"Tunisia","value":112974},{"name":"Turkey","value":183557},{"name":"Uganda","value":210483},{"name":"Ukraine","value":241368},{"name":"United Arab Emirates","value":770},{"name":"United Kingdom","value":414722},{"name":"United States of America","value":403552},{"name":"Uruguay","value":124721},{"name":"Uzbekistan","value":175822},{"name":"Venezuela","value":113909},{"name":"Vietnam","value":206804},{"name":"Yemen","value":31625},{"name":"Zambia","value":50227},{"name":"Zambia","value":55482}]}
